[{"_id": "582849314ab55e090c146016", "correct_answer": 1, "has_suggest_answer": false, "id": "582849314ab55e090c146016", "suggest_answer": ""}, {"_id": "582849314ab55e090c146018", "correct_answer": 4, "has_suggest_answer": true, "id": "582849314ab55e090c146018", "suggest_answer": {"blocks": [{"depth": 0, "entityRanges": [], "inlineStyleRanges": [], "key": "adtvl", "text": "Tất cả các thành phần HTML phải đặt trong cặp thẻ mở và đóng có dạng: <tag></tag>. Trừ một số thẻ đặc biệt không có thẻ đóng.", "type": "unstyled"}]}}, {"_id": "582849314ab55e090c14601a", "correct_answer": 2, "has_suggest_answer": true, "id": "582849314ab55e090c14601a", "suggest_answer": {"blocks": [{"depth": 0, "entityRanges": [], "inlineStyleRanges": [], "key": "buhbf", "text": "Ý của câu hỏi là thẻ nào dùng để mở đầu đoạn văn. Đó là thẻ <p> chứ còn gì nữa", "type": "unstyled"}]}}, {"_id": "582849324ab55e090c14601c", "correct_answer": 0, "has_suggest_answer": false, "id": "582849324ab55e090c14601c", "suggest_answer": ""}, {"_id": "582849324ab55e090c14601e", "correct_answer": 0, "has_suggest_answer": true, "id": "582849324ab55e090c14601e", "suggest_answer": {"blocks": [{"depth": 0, "entityRanges": [], "inlineStyleRanges": [], "key": "9p98b", "text": "Câu này rất đơn giản, tuy nhiên nếu bạn nào chưa gặp thì sẽ bối rối vcl ra", "type": "unstyled"}, {"depth": 0, "entityRanges": [], "inlineStyleRanges": [], "key": "60m7j", "text": "", "type": "unstyled"}, {"depth": 0, "entityRanges": [], "inlineStyleRanges": [], "key": "39odh", "text": "Theo W3C thì: The <!DOCTYPE> declaration must be the very first thing in your HTML document, before the <html> tag. The <!DOCTYPE> declaration is not an HTML tag; it is an instruction to the web browser about what version of HTML the page is written in. - <!DOCTYPE> phải được đặt đầu tiên trong tài liệu HTML , trước thẻ <html?. <!DOCTYPE> không phải là một thẻ HTML, nó chỉ có nhiệm vụ báo cho trình duyệt biết phiên bản đang sử dụng là phiên bản nào thôi. (Cũng dể hiểu mà nhỉ)you", "type": "unstyled"}]}}, {"_id": "582849324ab55e090c146020", "correct_answer": 0, "has_suggest_answer": true, "id": "582849324ab55e090c146020", "suggest_answer": {"blocks": [{"depth": 0, "entityRanges": [], "inlineStyleRanges": [], "key": "69sfi", "text": "A CSS comment starts with /* and ends with */. Comments can also span multiple lines:", "type": "unstyled"}, {"depth": 0, "entityRanges": [{"key": 0, "length": 1, "offset": 0}], "inlineStyleRanges": [], "key": "4ig2v", "text": " ", "type": "atomic"}, {"depth": 0, "entityRanges": [], "inlineStyleRanges": [], "key": "1rvua", "text": "", "type": "unstyled"}], "entityMap": {"0": {"data": {"content": "p {   \n\tcolor: red;    \n\t/* This is a single-line comment */  \n\ttext-align: center;\n}\n\n/* This is\na multi-line\ncomment */", "mode": "css", "name": ""}, "mutability": "IMMUTABLE", "type": "code-editor-block"}}}}, {"_id": "582849324ab55e090c146022", "correct_answer": 0, "has_suggest_answer": true, "id": "582849324ab55e090c146022", "suggest_answer": {"blocks": [{"depth": 0, "entityRanges": [], "inlineStyleRanges": [{"length": 1, "offset": 31, "style": "BOLD"}, {"length": 1, "offset": 41, "style": "BOLD"}], "key": "akp27", "text": "<ul></ul> là viết tắt của chữ: unordered list có nghĩa là danh sách không có thứ tự", "type": "unstyled"}]}}, {"_id": "582849324ab55e090c146024", "correct_answer": 0, "has_suggest_answer": true, "id": "582849324ab55e090c146024", "suggest_answer": {"blocks": [{"depth": 0, "entityRanges": [], "inlineStyleRanges": [{"length": 1, "offset": 31, "style": "BOLD"}, {"length": 1, "offset": 39, "style": "BOLD"}], "key": "b6l45", "text": "<ol></ol> là viết tắt của chữ \"ordered list\" có nghĩa là danh sách có thứ tự.", "type": "unstyled"}]}}, {"_id": "582849324ab55e090c146026", "correct_answer": 0, "has_suggest_answer": false, "id": "582849324ab55e090c146026", "suggest_answer": ""}, {"_id": "582849324ab55e090c146028", "correct_answer": 0, "has_suggest_answer": false, "id": "582849324ab55e090c146028", "suggest_answer": ""}, {"_id": "582849324ab55e090c14602a", "correct_answer": 0, "has_suggest_answer": false, "id": "582849324ab55e090c14602a", "suggest_answer": ""}, {"_id": "582849324ab55e090c14602c", "correct_answer": 1, "has_suggest_answer": true, "id": "582849324ab55e090c14602c", "suggest_answer": {"blocks": [{"depth": 0, "entityRanges": [], "inlineStyleRanges": [], "key": "jtdh", "text": "<!--This is a comment. Comments are not displayed in the browser-->", "type": "unstyled"}]}}, {"_id": "582849324ab55e090c14602e", "correct_answer": 1, "has_suggest_answer": false, "id": "582849324ab55e090c14602e", "suggest_answer": ""}, {"_id": "582849324ab55e090c146030", "correct_answer": 1, "has_suggest_answer": false, "id": "582849324ab55e090c146030", "suggest_answer": null}, {"_id": "582849324ab55e090c146032", "correct_answer": 0, "has_suggest_answer": true, "id": "582849324ab55e090c146032", "suggest_answer": {"blocks": [{"depth": 0, "entityRanges": [], "inlineStyleRanges": [], "key": "98thk", "text": "Padding là khoảng trống nằm giữa nội dung và viền (đường viền). Padding bao quanh 4 mặt của nội dung, tuy nhiên bạn có thể nhắm mục tiêu của padding và thay đổi padding của từng bên với css.", "type": "unstyled"}, {"depth": 0, "entityRanges": [], "inlineStyleRanges": [], "key": "331pf", "text": "\nMargin là khoảng trống nằm giữa viền và phần tử tiếp theo. Bạn cứ hiểu không gian tính từ viền tới các phần tử khác được gọi là margin. Cũng tương tự như padding thì margin cũng bao quanh 4 mặt và bạn có thể nhắm mục tiêu margin trên, dưới, trái, phải cho nó.\n", "type": "unstyled"}, {"depth": 0, "entityRanges": [], "inlineStyleRanges": [], "key": "9viiu", "text": "Để cụ thể hơn mình sẽ minh họa cho các bạn bằng hình ảnh sau đây.", "type": "unstyled"}, {"depth": 0, "entityRanges": [], "inlineStyleRanges": [], "key": "33u1v", "text": "", "type": "unstyled"}, {"depth": 0, "entityRanges": [{"key": 0, "length": 1, "offset": 0}], "inlineStyleRanges": [], "key": "cqs0v", "text": " ", "type": "atomic"}, {"depth": 0, "entityRanges": [], "inlineStyleRanges": [], "key": "81deb", "text": "", "type": "unstyled"}], "entityMap": {"0": {"data": {"src": "http://blog.seobymoz.com/wp-content/uploads/2015/07/CSS-Boxmodel.jpg"}, "mutability": "IMMUTABLE", "type": "image"}}}}, {"_id": "582849324ab55e090c146034", "correct_answer": 0, "has_suggest_answer": true, "id": "582849324ab55e090c146034", "suggest_answer": {"blocks": [{"depth": 0, "entityRanges": [], "inlineStyleRanges": [], "key": "a60n8", "text": "Padding là khoảng trống nằm giữa nội dung và viền (đường viền). Padding bao quanh 4 mặt của nội dung, tuy nhiên bạn có thể nhắm mục tiêu của padding và thay đổi padding của từng bên với css.", "type": "unstyled"}]}}, {"_id": "582849324ab55e090c146036", "correct_answer": 1, "has_suggest_answer": true, "id": "582849324ab55e090c146036", "suggest_answer": {"blocks": [{"depth": 0, "entityRanges": [], "inlineStyleRanges": [{"length": 6, "offset": 4, "style": "CODE"}], "key": "495kc", "text": "The margin property is a shorthand property for the following individual margin properties:", "type": "unstyled"}, {"depth": 0, "entityRanges": [], "inlineStyleRanges": [{"length": 10, "offset": 0, "style": "CODE"}], "key": "2v9bp", "text": "margin-top", "type": "unordered-list-item"}, {"depth": 0, "entityRanges": [], "inlineStyleRanges": [{"length": 12, "offset": 0, "style": "CODE"}], "key": "7454r", "text": "margin-right", "type": "unordered-list-item"}, {"depth": 0, "entityRanges": [], "inlineStyleRanges": [{"length": 13, "offset": 0, "style": "CODE"}], "key": "49ncs", "text": "margin-bottom", "type": "unordered-list-item"}, {"depth": 0, "entityRanges": [], "inlineStyleRanges": [{"length": 11, "offset": 0, "style": "CODE"}], "key": "bk498", "text": "margin-left", "type": "unordered-list-item"}]}}, {"_id": "582849324ab55e090c146038", "correct_answer": 3, "has_suggest_answer": false, "id": "582849324ab55e090c146038", "suggest_answer": ""}, {"_id": "582849324ab55e090c14603a", "correct_answer": 1, "has_suggest_answer": true, "id": "582849324ab55e090c14603a", "suggest_answer": {"blocks": [{"depth": 0, "entityRanges": [], "inlineStyleRanges": [{"length": 3, "offset": 49, "style": "CODE"}], "key": "h159", "text": "Để hiển thị hình ảnh lên web thì bạn sử dụng thẻ img với cú pháp sau:", "type": "unstyled"}, {"depth": 0, "entityRanges": [], "inlineStyleRanges": [], "key": "eg1nv", "text": "", "type": "unstyled"}, {"depth": 0, "entityRanges": [{"key": 0, "length": 1, "offset": 0}], "inlineStyleRanges": [], "key": "a91s5", "text": " ", "type": "atomic"}, {"depth": 0, "entityRanges": [], "inlineStyleRanges": [], "key": "8cp9d", "text": "", "type": "unstyled"}], "entityMap": {"0": {"data": {"content": "<img src=\"url_to_image\"/>", "mode": "htmlmixed", "name": ""}, "mutability": "IMMUTABLE", "type": "code-editor-block"}}}}, {"_id": "582849324ab55e090c14603c", "correct_answer": 0, "has_suggest_answer": true, "id": "582849324ab55e090c14603c", "suggest_answer": {"blocks": [{"depth": 0, "entityRanges": [], "inlineStyleRanges": [], "key": "29dki", "text": "Thuộc tính alt: Đây là thuộc tính sẽ hiển thị cho trường hợp bạn truyền URL image bị sai. Nghĩa là nó sẽ hiển thị đoạn text này thay vì hình ảnh nếu URL bạn truyền vào bị sai.", "type": "unstyled"}]}}, {"_id": "582849324ab55e090c14603e", "correct_answer": 4, "has_suggest_answer": false, "id": "582849324ab55e090c14603e", "suggest_answer": ""}, {"_id": "582849324ab55e090c146040", "correct_answer": 0, "has_suggest_answer": false, "id": "582849324ab55e090c146040", "suggest_answer": ""}, {"_id": "582849324ab55e090c146042", "correct_answer": 1, "has_suggest_answer": false, "id": "582849324ab55e090c146042", "suggest_answer": ""}, {"_id": "582849324ab55e090c146044", "correct_answer": 0, "has_suggest_answer": true, "id": "582849324ab55e090c146044", "suggest_answer": {"blocks": [{"depth": 0, "entityRanges": [], "inlineStyleRanges": [], "key": "7csj1", "text": "Đây là cú pháp chuẩn của Bootstrap, bạn không thể nào làm khác được đâu", "type": "unstyled"}]}}, {"_id": "582849324ab55e090c146046", "correct_answer": 1, "has_suggest_answer": false, "id": "582849324ab55e090c146046", "suggest_answer": ""}, {"_id": "582849324ab55e090c146048", "correct_answer": 2, "has_suggest_answer": true, "id": "582849324ab55e090c146048", "suggest_answer": {"blocks": [{"depth": 0, "entityRanges": [], "inlineStyleRanges": [], "key": "ei37n", "text": "Bootstrap được chia làm 12 cột", "type": "unstyled"}]}}, {"_id": "582849324ab55e090c14604a", "correct_answer": 1, "has_suggest_answer": true, "id": "582849324ab55e090c14604a", "suggest_answer": {"blocks": [{"depth": 0, "entityRanges": [], "inlineStyleRanges": [], "key": "53c5h", "text": "Đường dẫn như vầy được gọi là đường dẫn tương đối", "type": "unstyled"}]}}, {"_id": "582849324ab55e090c14604c", "correct_answer": 0, "has_suggest_answer": true, "id": "582849324ab55e090c14604c", "suggest_answer": {"blocks": [{"depth": 0, "entityRanges": [], "inlineStyleRanges": [], "key": "129el", "text": "Đường dẫn như vầy được gọi là đường dẫn tiệt đối", "type": "unstyled"}]}}, {"_id": "582849324ab55e090c14604e", "correct_answer": 0, "has_suggest_answer": false, "id": "582849324ab55e090c14604e", "suggest_answer": ""}, {"_id": "582849324ab55e090c146050", "correct_answer": 0, "has_suggest_answer": false, "id": "582849324ab55e090c146050", "suggest_answer": ""}, {"_id": "582849324ab55e090c146052", "correct_answer": 0, "has_suggest_answer": true, "id": "582849324ab55e090c146052", "suggest_answer": {"blocks": [{"depth": 0, "entityRanges": [], "inlineStyleRanges": [], "key": "cf88t", "text": "ID là duy nhất và Class được sử dụng nhiều lần.", "type": "unstyled"}]}}, {"_id": "582849324ab55e090c146054", "correct_answer": 3, "has_suggest_answer": true, "id": "582849324ab55e090c146054", "suggest_answer": {"blocks": [{"depth": 0, "entityRanges": [], "inlineStyleRanges": [], "key": "5c7et", "text": "# tượng trưng cho id và . tượng trưng cho class", "type": "unstyled"}]}}, {"_id": "582849324ab55e090c146056", "correct_answer": 4, "has_suggest_answer": true, "id": "582849324ab55e090c146056", "suggest_answer": {"blocks": [{"depth": 0, "entityRanges": [], "inlineStyleRanges": [], "key": "2qlbu", "text": "# tượng trưng cho id và . tượng trưng cho class", "type": "unstyled"}]}}, {"_id": "582849324ab55e090c146058", "correct_answer": 0, "has_suggest_answer": false, "id": "582849324ab55e090c146058", "suggest_answer": ""}, {"_id": "582849324ab55e090c14605a", "correct_answer": 2, "has_suggest_answer": false, "id": "582849324ab55e090c14605a", "suggest_answer": ""}, {"_id": "582849324ab55e090c14605c", "correct_answer": 1, "has_suggest_answer": false, "id": "582849324ab55e090c14605c", "suggest_answer": ""}, {"_id": "582849324ab55e090c14605e", "correct_answer": 1, "has_suggest_answer": false, "id": "582849324ab55e090c14605e", "suggest_answer": ""}, {"_id": "582849324ab55e090c146060", "correct_answer": 2, "has_suggest_answer": false, "id": "582849324ab55e090c146060", "suggest_answer": ""}, {"_id": "582849324ab55e090c146062", "correct_answer": 1, "has_suggest_answer": true, "id": "582849324ab55e090c146062", "suggest_answer": {"blocks": [{"depth": 0, "entityRanges": [], "inlineStyleRanges": [{"length": 11, "offset": 0, "style": "BOLD"}], "key": "evb94", "text": "Thẻ tiêu đề (hay còn gọi là mục tiêu đề) là phần nội dung miêu tả ngắn gọn và chính xác nhất nội dụng bên trong của trang. Bắt buộc phải có đối với các văn bản HTML/XHTML, luôn được đặt trong phần header.", "type": "unstyled"}]}}]