[{"__v": 0, "_id": "596eec4094f4c20939de4ed8", "answers": [{"answer": {"blocks": [{"depth": 0, "entityRanges": [], "inlineStyleRanges": [], "key": "d3jsf", "text": "growling", "type": "unstyled"}]}, "id": "question1500495429538", "type": "editor"}, {"answer": {"blocks": [{"depth": 0, "entityRanges": [], "inlineStyleRanges": [], "key": "1ot9p", "text": "roaring", "type": "unstyled"}]}, "id": "question1500495451508", "type": "editor"}, {"answer": {"blocks": [{"depth": 0, "entityRanges": [], "inlineStyleRanges": [], "key": "bte01", "text": "barkling", "type": "unstyled"}]}, "id": "question1500495454252", "type": "editor"}, {"answer": {"blocks": [{"depth": 0, "entityRanges": [], "inlineStyleRanges": [], "key": "a6qc0", "text": "howling", "type": "unstyled"}]}, "id": "question1500495456191", "type": "editor"}], "created_at": "2017-07-19T05:21:04.531Z", "has_suggest_answer": true, "id": "596eec4094f4c20939de4ed8", "question": {"blocks": [{"depth": 0, "entityRanges": [], "inlineStyleRanges": [], "key": "4rrrv", "text": "The heard ..... of wolves mournfully in the nearby forest", "type": "unstyled"}]}, "type": "multiple_choose", "updated_at": "2017-07-20T15:58:43.342Z"}, {"__v": 0, "_id": "596eec4094f4c20939de4eda", "answers": [{"answer": {"blocks": [{"depth": 0, "entityRanges": [], "inlineStyleRanges": [], "key": "568or", "text": "so old", "type": "unstyled"}]}, "id": "question1500495459329", "type": "editor"}, {"answer": {"blocks": [{"depth": 0, "entityRanges": [], "inlineStyleRanges": [], "key": "8ngo1", "text": "old enough", "type": "unstyled"}]}, "id": "question1500495482183", "type": "editor"}, {"answer": {"blocks": [{"depth": 0, "entityRanges": [], "inlineStyleRanges": [], "key": "4qnr9", "text": "enough old", "type": "unstyled"}]}, "id": "question1500495483307", "type": "editor"}, {"answer": {"blocks": [{"depth": 0, "entityRanges": [], "inlineStyleRanges": [], "key": "2d6ps", "text": "as old", "type": "unstyled"}]}, "id": "question1500495485664", "type": "editor"}], "created_at": "2017-07-19T05:21:04.547Z", "has_suggest_answer": true, "id": "596eec4094f4c20939de4eda", "question": {"blocks": [{"depth": 0, "entityRanges": [], "inlineStyleRanges": [], "key": "fc6tk", "text": "They are not ...... to take part in this program of the World Health Organization", "type": "unstyled"}]}, "type": "multiple_choose", "updated_at": "2017-07-20T15:58:43.394Z"}, {"__v": 0, "_id": "596eec4094f4c20939de4edc", "answers": [{"answer": {"blocks": [{"depth": 0, "entityRanges": [], "inlineStyleRanges": [], "key": "2mlqg", "text": "away", "type": "unstyled"}]}, "id": "question1500495488078", "type": "editor"}, {"answer": {"blocks": [{"depth": 0, "entityRanges": [], "inlineStyleRanges": [], "key": "c2o4n", "text": "over", "type": "unstyled"}]}, "id": "question1500495503059", "type": "editor"}, {"answer": {"blocks": [{"depth": 0, "entityRanges": [], "inlineStyleRanges": [], "key": "92cd8", "text": "in", "type": "unstyled"}]}, "id": "question1500495505450", "type": "editor"}, {"answer": {"blocks": [{"depth": 0, "entityRanges": [], "inlineStyleRanges": [], "key": "6cfae", "text": "after", "type": "unstyled"}]}, "id": "question1500495508235", "type": "editor"}], "created_at": "2017-07-19T05:21:04.554Z", "has_suggest_answer": true, "id": "596eec4094f4c20939de4edc", "question": {"blocks": [{"depth": 0, "entityRanges": [], "inlineStyleRanges": [], "key": "6qbk", "text": "I'm going ..... for a few days so don't send me any more work", "type": "unstyled"}]}, "type": "multiple_choose", "updated_at": "2017-07-20T15:58:43.419Z"}, {"__v": 0, "_id": "596eec4094f4c20939de4ede", "answers": [{"answer": {"blocks": [{"depth": 0, "entityRanges": [], "inlineStyleRanges": [], "key": "2o49", "text": "biology", "type": "unstyled"}]}, "id": "question1500495509314", "type": "editor"}, {"answer": {"blocks": [{"depth": 0, "entityRanges": [], "inlineStyleRanges": [], "key": "br3st", "text": "biologically", "type": "unstyled"}]}, "id": "question1500495521578", "type": "editor"}, {"answer": {"blocks": [{"depth": 0, "entityRanges": [], "inlineStyleRanges": [], "key": "6sn8b", "text": "biologist", "type": "unstyled"}]}, "id": "question1500495523669", "type": "editor"}, {"answer": {"blocks": [{"depth": 0, "entityRanges": [], "inlineStyleRanges": [], "key": "3tqf", "text": "biological", "type": "unstyled"}]}, "id": "question1500495525735", "type": "editor"}], "created_at": "2017-07-19T05:21:04.559Z", "has_suggest_answer": true, "id": "596eec4094f4c20939de4ede", "question": {"blocks": [{"depth": 0, "entityRanges": [], "inlineStyleRanges": [], "key": "c6d6v", "text": "A scientist who studies living things is a ......", "type": "unstyled"}]}, "type": "multiple_choose", "updated_at": "2017-07-20T15:58:43.454Z"}, {"__v": 0, "_id": "596eec4094f4c20939de4ee0", "answers": [{"answer": {"blocks": [{"depth": 0, "entityRanges": [], "inlineStyleRanges": [], "key": "f7017", "text": "despite", "type": "unstyled"}]}, "id": "question1500495527827", "type": "editor"}, {"answer": {"blocks": [{"depth": 0, "entityRanges": [], "inlineStyleRanges": [], "key": "dk6mt", "text": "in spite", "type": "unstyled"}]}, "id": "question1500495548609", "type": "editor"}, {"answer": {"blocks": [{"depth": 0, "entityRanges": [], "inlineStyleRanges": [], "key": "c2s3p", "text": "because", "type": "unstyled"}]}, "id": "question1500495551656", "type": "editor"}, {"answer": {"blocks": [{"depth": 0, "entityRanges": [], "inlineStyleRanges": [], "key": "9upi7", "text": "because of ", "type": "unstyled"}]}, "id": "question1500495553893", "type": "editor"}], "created_at": "2017-07-19T05:21:04.565Z", "has_suggest_answer": true, "id": "596eec4094f4c20939de4ee0", "question": {"blocks": [{"depth": 0, "entityRanges": [], "inlineStyleRanges": [], "key": "dq4nk", "text": "The football match was postponed ..... the bad weather", "type": "unstyled"}]}, "type": "multiple_choose", "updated_at": "2017-07-20T15:58:43.469Z"}]