[{"_id": "59c0e92d0cf8616ca576730c", "correct_answer": 1, "has_suggest_answer": true, "id": "59c0e92d0cf8616ca576730c", "suggest_answer": {"blocks": [{"depth": 0, "entityRanges": [], "inlineStyleRanges": [], "key": "8s8as", "text": "well-paid job: công việc được trả lương cao", "type": "unstyled"}]}}, {"_id": "59c0e92d0cf8616ca576730e", "correct_answer": 2, "has_suggest_answer": true, "id": "59c0e92d0cf8616ca576730e", "suggest_answer": {"blocks": [{"depth": 0, "entityRanges": [], "inlineStyleRanges": [], "key": "cn794", "text": "chỗ trống cần điền một tính từ", "type": "unstyled"}, {"depth": 0, "entityRanges": [], "inlineStyleRanges": [], "key": "58q99", "text": "respectable: đứng đắn, chỉnh tề", "type": "unstyled"}, {"depth": 0, "entityRanges": [], "inlineStyleRanges": [], "key": "8t966", "text": "respectful: tôn trọng, tôn kính", "type": "unstyled"}]}}, {"_id": "59c0e92d0cf8616ca5767310", "correct_answer": 0, "has_suggest_answer": true, "id": "59c0e92d0cf8616ca5767310", "suggest_answer": {"blocks": [{"depth": 0, "entityRanges": [], "inlineStyleRanges": [], "key": "am7qb", "text": "take back: rút lại", "type": "unstyled"}]}}, {"_id": "59c0e92d0cf8616ca5767312", "correct_answer": 0, "has_suggest_answer": true, "id": "59c0e92d0cf8616ca5767312", "suggest_answer": {"blocks": [{"depth": 0, "entityRanges": [], "inlineStyleRanges": [], "key": "90bnk", "text": "\"Tôi lạc đường rồi! Đây có phải đường đến bưu điện không?\"", "type": "unstyled"}, {"depth": 0, "entityRanges": [], "inlineStyleRanges": [], "key": "8k6js", "text": "\"Tôi e là không phải đâu.\"", "type": "unstyled"}]}}, {"_id": "59c0e92d0cf8616ca5767314", "correct_answer": 0, "has_suggest_answer": true, "id": "59c0e92d0cf8616ca5767314", "suggest_answer": {"blocks": [{"depth": 0, "entityRanges": [], "inlineStyleRanges": [], "key": "ebt3", "text": "sympathetic: biết thông cảm", "type": "unstyled"}]}}]