[{"_id": "592b9e14be43467abbd1bfcc", "correct_answer": 0, "has_suggest_answer": false, "id": "592b9e14be43467abbd1bfcc", "suggest_answer": ""}, {"_id": "592b9e14be43467abbd1bfce", "correct_answer": 2, "has_suggest_answer": false, "id": "592b9e14be43467abbd1bfce", "suggest_answer": ""}, {"_id": "592b9e14be43467abbd1bfd0", "correct_answer": 1, "has_suggest_answer": false, "id": "592b9e14be43467abbd1bfd0", "suggest_answer": ""}, {"_id": "592b9e14be43467abbd1bfd2", "correct_answer": 2, "has_suggest_answer": false, "id": "592b9e14be43467abbd1bfd2", "suggest_answer": ""}, {"_id": "592b9e14be43467abbd1bfd4", "correct_answer": 0, "has_suggest_answer": false, "id": "592b9e14be43467abbd1bfd4", "suggest_answer": ""}, {"_id": "592b9e14be43467abbd1bfd6", "correct_answer": 1, "has_suggest_answer": false, "id": "592b9e14be43467abbd1bfd6", "suggest_answer": ""}, {"_id": "592b9e14be43467abbd1bfd8", "correct_answer": 3, "has_suggest_answer": false, "id": "592b9e14be43467abbd1bfd8", "suggest_answer": ""}, {"_id": "592b9e14be43467abbd1bfda", "correct_answer": 1, "has_suggest_answer": false, "id": "592b9e14be43467abbd1bfda", "suggest_answer": ""}, {"_id": "592b9e14be43467abbd1bfdc", "correct_answer": 1, "has_suggest_answer": false, "id": "592b9e14be43467abbd1bfdc", "suggest_answer": ""}, {"_id": "592b9e14be43467abbd1bfde", "correct_answer": 2, "has_suggest_answer": false, "id": "592b9e14be43467abbd1bfde", "suggest_answer": ""}, {"_id": "592b9e14be43467abbd1bfe0", "correct_answer": 2, "has_suggest_answer": false, "id": "592b9e14be43467abbd1bfe0", "suggest_answer": ""}, {"_id": "592b9e14be43467abbd1bfe2", "correct_answer": 3, "has_suggest_answer": false, "id": "592b9e14be43467abbd1bfe2", "suggest_answer": ""}, {"_id": "592b9e14be43467abbd1bfe4", "correct_answer": 2, "has_suggest_answer": false, "id": "592b9e14be43467abbd1bfe4", "suggest_answer": ""}, {"_id": "592b9e14be43467abbd1bfe6", "correct_answer": 3, "has_suggest_answer": false, "id": "592b9e14be43467abbd1bfe6", "suggest_answer": ""}, {"_id": "592b9e14be43467abbd1bfe8", "correct_answer": 1, "has_suggest_answer": false, "id": "592b9e14be43467abbd1bfe8", "suggest_answer": ""}, {"_id": "592b9e14be43467abbd1bfea", "correct_answer": 3, "has_suggest_answer": false, "id": "592b9e14be43467abbd1bfea", "suggest_answer": ""}, {"_id": "592b9e14be43467abbd1bfec", "correct_answer": 2, "has_suggest_answer": false, "id": "592b9e14be43467abbd1bfec", "suggest_answer": ""}, {"_id": "592b9e14be43467abbd1bfee", "correct_answer": 0, "has_suggest_answer": false, "id": "592b9e14be43467abbd1bfee", "suggest_answer": ""}, {"_id": "592b9e14be43467abbd1bff0", "correct_answer": 1, "has_suggest_answer": false, "id": "592b9e14be43467abbd1bff0", "suggest_answer": ""}, {"_id": "592b9e14be43467abbd1bff2", "correct_answer": 0, "has_suggest_answer": false, "id": "592b9e14be43467abbd1bff2", "suggest_answer": ""}, {"_id": "592b9e14be43467abbd1bff4", "correct_answer": 1, "has_suggest_answer": false, "id": "592b9e14be43467abbd1bff4", "suggest_answer": ""}, {"_id": "592b9e14be43467abbd1bff6", "correct_answer": 3, "has_suggest_answer": false, "id": "592b9e14be43467abbd1bff6", "suggest_answer": ""}, {"_id": "592b9e14be43467abbd1bff8", "correct_answer": 3, "has_suggest_answer": false, "id": "592b9e14be43467abbd1bff8", "suggest_answer": ""}, {"_id": "592b9e14be43467abbd1bffa", "correct_answer": 0, "has_suggest_answer": false, "id": "592b9e14be43467abbd1bffa", "suggest_answer": ""}, {"_id": "592b9e14be43467abbd1bffc", "correct_answer": 0, "has_suggest_answer": false, "id": "592b9e14be43467abbd1bffc", "suggest_answer": ""}, {"_id": "592b9e14be43467abbd1bffe", "correct_answer": 3, "has_suggest_answer": false, "id": "592b9e14be43467abbd1bffe", "suggest_answer": ""}, {"_id": "592b9e14be43467abbd1c000", "correct_answer": 0, "has_suggest_answer": false, "id": "592b9e14be43467abbd1c000", "suggest_answer": ""}, {"_id": "592b9e14be43467abbd1c002", "correct_answer": 0, "has_suggest_answer": false, "id": "592b9e14be43467abbd1c002", "suggest_answer": ""}, {"_id": "592b9e14be43467abbd1c004", "correct_answer": 1, "has_suggest_answer": false, "id": "592b9e14be43467abbd1c004", "suggest_answer": ""}, {"_id": "592b9e14be43467abbd1c006", "correct_answer": 0, "has_suggest_answer": false, "id": "592b9e14be43467abbd1c006", "suggest_answer": ""}, {"_id": "592b9e14be43467abbd1c008", "correct_answer": 2, "has_suggest_answer": false, "id": "592b9e14be43467abbd1c008", "suggest_answer": ""}, {"_id": "592b9e14be43467abbd1c00a", "correct_answer": 2, "has_suggest_answer": false, "id": "592b9e14be43467abbd1c00a", "suggest_answer": ""}, {"_id": "592b9e14be43467abbd1c00c", "correct_answer": 1, "has_suggest_answer": false, "id": "592b9e14be43467abbd1c00c", "suggest_answer": ""}, {"_id": "592b9e14be43467abbd1c00e", "correct_answer": 2, "has_suggest_answer": false, "id": "592b9e14be43467abbd1c00e", "suggest_answer": ""}, {"_id": "592b9e14be43467abbd1c010", "correct_answer": 3, "has_suggest_answer": false, "id": "592b9e14be43467abbd1c010", "suggest_answer": ""}, {"_id": "592b9e14be43467abbd1c012", "correct_answer": 1, "has_suggest_answer": false, "id": "592b9e14be43467abbd1c012", "suggest_answer": ""}, {"_id": "592b9e14be43467abbd1c014", "correct_answer": 0, "has_suggest_answer": false, "id": "592b9e14be43467abbd1c014", "suggest_answer": ""}, {"_id": "592b9e14be43467abbd1c016", "correct_answer": 3, "has_suggest_answer": false, "id": "592b9e14be43467abbd1c016", "suggest_answer": ""}, {"_id": "592b9e14be43467abbd1c018", "correct_answer": 2, "has_suggest_answer": false, "id": "592b9e14be43467abbd1c018", "suggest_answer": ""}, {"_id": "592b9e14be43467abbd1c01a", "correct_answer": 3, "has_suggest_answer": false, "id": "592b9e14be43467abbd1c01a", "suggest_answer": ""}]